{
    "gridWidth": 8,
    "gridHeight": 8,
    "hasTime": true,
    "time": 60,
    "walls": [
        {
            "orderIndex": 5,
            "lenght": 2,
            "color": 1
        },
        {
            "orderIndex": 9,
            "lenght": 2,
            "color": 4
        },
        {
            "orderIndex": 13,
            "lenght": 3,
            "color": 5
        },
        {
            "orderIndex": 20,
            "lenght": 3,
            "color": 6
        },
        {
            "orderIndex": 24,
            "lenght": 3,
            "color": 6
        },
        {
            "orderIndex": 17,
            "lenght": 1,
            "color": 3
        },
        {
            "orderIndex": 12,
            "lenght": 1,
            "color": 0
        }
    ],
    "blocks": [
        {
            "blockIndex": 1,
            "blockColor": 0,
            "worldPosition": {
                "x": 4.0,
                "y": 0.0
            },
            "Lock": true,
            "ice": false
        },
        {
            "blockIndex": 2,
            "blockColor": 1,
            "worldPosition": {
                "x": 5.0,
                "y": 4.0
            },
            "Lock": true,
            "ice": false
        },
        {
            "blockIndex": 4,
            "blockColor": 4,
            "worldPosition": {
                "x": 3.0,
                "y": 3.0
            },
            "Lock": false,
            "ice": true
        },
        {
            "blockIndex": 5,
            "blockColor": 3,
            "worldPosition": {
                "x": 5.0,
                "y": 6.0
            },
            "Lock": false,
            "ice": false
        },
        {
            "blockIndex": 2,
            "blockColor": 4,
            "worldPosition": {
                "x": 0.0,
                "y": 5.0
            },
            "Lock": false,
            "ice": false
        },
        {
            "blockIndex": 7,
            "blockColor": 5,
            "worldPosition": {
                "x": 1.0,
                "y": 1.0
            },
            "Lock": false,
            "ice": false
        },
        {
            "blockIndex": 6,
            "blockColor": 6,
            "worldPosition": {
                "x": 5.0,
                "y": 1.0
            },
            "Lock": false,
            "ice": false
        }
    ],
    "cameraSettings": {
        "x": -5.0,
        "y": 30.0,
        "z": 0.0
    },
    "cameraCenter": {
        "x": 3.5,
        "y": 0.0,
        "z": 3.5
    }
}